multitimer.py
multitimer-0.3.dist-info/LICENSE.txt
multitimer-0.3.dist-info/METADATA
multitimer-0.3.dist-info/WHEEL
multitimer-0.3.dist-info/top_level.txt
multitimer-0.3.dist-info/RECORD
